sqlalchemy_serverless_aurora_plugin/__init__.py
sqlalchemy_serverless_aurora_plugin-0.2.5.dist-info/LICENSE
sqlalchemy_serverless_aurora_plugin-0.2.5.dist-info/METADATA
sqlalchemy_serverless_aurora_plugin-0.2.5.dist-info/WHEEL
sqlalchemy_serverless_aurora_plugin-0.2.5.dist-info/entry_points.txt
sqlalchemy_serverless_aurora_plugin-0.2.5.dist-info/top_level.txt
sqlalchemy_serverless_aurora_plugin-0.2.5.dist-info/RECORD
