Metadata-Version: 2.1
Name: sqlalchemy-serverless-aurora-plugin
Version: 0.2.5
Summary: A fork of sqlalchemy-aurora-data-api
Home-page: https://github.com/duncankoss/sqlalchemy-serverless-aurora-plugin
Author: dkoss
Author-email: UNKNOWN
License: Apache Software License
Platform: MacOS X
Platform: Posix
Classifier: Intended Audience :: Developers
Classifier: License :: OSI Approved :: Apache Software License
Classifier: Operating System :: MacOS :: MacOS X
Classifier: Operating System :: POSIX
Classifier: Programming Language :: Python
Classifier: Programming Language :: Python :: 2.7
Classifier: Programming Language :: Python :: 3.3
Classifier: Programming Language :: Python :: 3.4
Classifier: Programming Language :: Python :: 3.5
Classifier: Topic :: Software Development :: Libraries :: Python Modules
Requires-Dist: sqlalchemy
Requires-Dist: serverless-aurora (>=0.2.3)
